.editorconfig
.gitignore
.gitlab-ci.yml
LICENSE
README.rst
publish.settings.sh
publish.sh
pyproject.toml
.idea/modules.xml
.idea/peek-field-service.iml
.idea/inspectionProfiles/Project_Default.xml
.idea/inspectionProfiles/profiles_settings.xml
peek_field_service/PeekClientConfig.py
peek_field_service/PeekClientConfigTest.py
peek_field_service/PlatformDependencyTest.py
peek_field_service/__init__.py
peek_field_service/run_peek_field_service.py
peek_field_service/run_peek_field_service_build_only.py
peek_field_service/run_peek_field_service_offline.py
peek_field_service/winsvc_peek_client.py
peek_field_service.egg-info/PKG-INFO
peek_field_service.egg-info/SOURCES.txt
peek_field_service.egg-info/dependency_links.txt
peek_field_service.egg-info/entry_points.txt
peek_field_service.egg-info/requires.txt
peek_field_service.egg-info/top_level.txt
peek_field_service/backend/ClientObservable.py
peek_field_service/backend/SiteRootResource.py
peek_field_service/backend/__init__.py
peek_field_service/plugin/ClientFrontendBuildersMixin.py
peek_field_service/plugin/ClientPluginLoader.py
peek_field_service/plugin/ClientPluginLoaderTest.py
peek_field_service/plugin/PeekClientPlatformHook.py
peek_field_service/plugin/__init__.py
peek_field_service/sw_install/PeekSwInstallManager.py
peek_field_service/sw_install/PluginSwInstallManager.py
peek_field_service/sw_install/__init__.py