Metadata-Version: 2.4
Name: peek-field-service
Version: 5.0.4
Summary: Peek Field Service - where Peek Field App is served
Author-email: Synerty <contact@synerty.com>
Project-URL: Homepage, https://github.com/Synerty/peek-field-service
Keywords: Peek,Python,Platform,synerty
License-File: LICENSE
Requires-Dist: peek-plugin-base==5.0.4
Requires-Dist: peek-platform==5.0.4
Requires-Dist: peek-field-app==5.0.4
Requires-Dist: peek-field-doc==5.0.4
Dynamic: license-file
